click_aliases/__init__.py
click_aliases-1.0.3.dist-info/LICENSE
click_aliases-1.0.3.dist-info/METADATA
click_aliases-1.0.3.dist-info/WHEEL
click_aliases-1.0.3.dist-info/RECORD
