Metadata-Version: 2.1
Name: click-aliases
Version: 1.0.3
Summary: Add (mutiple) aliases to a click group or command
License: MIT
Author: Robbin Bonthond
Author-email: robbin@bonthond.com
Requires-Python: >=3.8,<4.0
Classifier: License :: OSI Approved :: MIT License
Classifier: Programming Language :: Python :: 3
Classifier: Programming Language :: Python :: 3.8
Classifier: Programming Language :: Python :: 3.9
Classifier: Programming Language :: Python :: 3.10
Classifier: Programming Language :: Python :: 3.11
Classifier: Programming Language :: Python :: 3.12
Requires-Dist: click (>=8.1.7,<9.0.0)
